{
    "global": {
        "cookie": "__hdnea__=st=1761471001~exp=1761557401~acl=/*~hmac=68aab419bd378ee2b58bec495a62fcaa063252d56317923dd0e70a76b5661e9c",
        "start": "26 Oct 2025 | 03:00 PM",
        "expiry": "27 Oct 2025 | 03:00 PM"
    },
    "plus": {
        "cookie": "__hdnea__=st=1761471002~exp=1761557402~acl=/*~hmac=3d906dfcf118082aeaec51584ddbd5f873f835cce025d0d97c42081f71d5efc3",
        "start": "26 Oct 2025 | 03:00 PM",
        "expiry": "27 Oct 2025 | 03:00 PM"
    },
    "ios": {
        "cookie": "__hdnea__=st=1761471002~exp=1761557402~acl=/*~hmac=3d906dfcf118082aeaec51584ddbd5f873f835cce025d0d97c42081f71d5efc3",
        "start": "26 Oct 2025 | 03:00 PM",
        "expiry": "27 Oct 2025 | 03:00 PM"
    }
}